pyqalloy/__init__.py
pyqalloy/core/__init__.py
pyqalloy/core/pyqalloy.py
pyqalloy/curation/__init__.py
pyqalloy/curation/analysis.py
pyqalloy/tests/test_AllDataAnalyzer.py
pyqalloy/tests/test_DBOverrideInSCA.py
pyqalloy/tests/test_SingleCompositionAnalyzer.py
pyqalloy/tests/test_SingleDOIAnalyzer.py
pyqalloy/tests/test_UtilityFunctions.py
pyqalloy-0.3.9.dist-info/LICENSE
pyqalloy-0.3.9.dist-info/METADATA
pyqalloy-0.3.9.dist-info/WHEEL
pyqalloy-0.3.9.dist-info/top_level.txt
pyqalloy-0.3.9.dist-info/RECORD
