Metadata-Version: 2.1
Name: pyqalloy
Version: 0.3.9
Summary: PyQAlloy is a tool for detection of abnormal data in alloy datasets (and other chemical spaces), allowing removal of hard-to-find erros in the data which often introduce systematic errors throwing off machine learning and researchers alike. Its development is a part of ULTERA Project carried under the DOE ARPA-E ULTIMATE program that aims to develop a new generation of materials for turbine blades and related applications.
Author-email: Adam Krajewski <ak@psu.edu>
Project-URL: Research Page, https://ultera.org
Project-URL: Homepage, https://pyqalloy.ultera.org
Project-URL: Bug Tracker, https://github.com/PhasesResearchLab/PyQAlloy/issues
Classifier: Programming Language :: Python :: 3
Classifier: Programming Language :: Python :: 3.9
Classifier: Programming Language :: Python :: 3.10
Classifier: Programming Language :: Python :: 3.11
Classifier: Development Status :: 4 - Beta
Classifier: Intended Audience :: Science/Research
Classifier: License :: OSI Approved :: MIT License
Classifier: Operating System :: OS Independent
Classifier: Topic :: Scientific/Engineering
Classifier: Topic :: Scientific/Engineering :: Artificial Intelligence
Classifier: Topic :: Scientific/Engineering :: Chemistry
Classifier: Topic :: Scientific/Engineering :: Physics
Classifier: Topic :: Scientific/Engineering :: Information Analysis
Classifier: Topic :: Software Development :: Quality Assurance
Requires-Python: >=3.9
License-File: LICENSE
Requires-Dist: pymatgen >=2024.2.20
Requires-Dist: numpy <2.0.0,>=1.25.0
Requires-Dist: tqdm >=4.63.0
Requires-Dist: natsort >=8.0.0
Requires-Dist: pymongo >=4.2
Requires-Dist: pySmartDL >=1.3.4
Requires-Dist: dnspython
Requires-Dist: scikit-learn
Requires-Dist: plotly
Requires-Dist: xlsxwriter
Requires-Dist: kaleido
Requires-Dist: montydb >=2.5.2
